phaselab/__init__.py
phaselab/chromatin/__init__.py
phaselab/chromatin/accessibility.py
phaselab/chromatin/atac_integration.py
phaselab/chromatin/integration.py
phaselab/chromatin/methylation.py
phaselab/chromatin/nucleosome.py
phaselab/chromatin/tissue_models.py
phaselab/circadian/__init__.py
phaselab/circadian/kuramoto.py
phaselab/circadian/multi_tissue.py
phaselab/circadian/sms_model.py
phaselab/core/__init__.py
phaselab/core/coherence.py
phaselab/core/constants.py
phaselab/core/hamiltonians.py
phaselab/crispr/__init__.py
phaselab/crispr/base_editing.py
phaselab/crispr/coherence_utils.py
phaselab/crispr/editors.py
phaselab/crispr/enhancer.py
phaselab/crispr/interference.py
phaselab/crispr/knockout.py
phaselab/crispr/multiguide.py
phaselab/crispr/pam_scan.py
phaselab/crispr/pipeline.py
phaselab/crispr/prime_editing.py
phaselab/crispr/scoring.py
phaselab/delivery/__init__.py
phaselab/delivery/aav.py
phaselab/delivery/immunogenicity.py
phaselab/drug/__init__.py
phaselab/drug/chronotherapy.py
phaselab/drug/pharmacokinetics.py
phaselab/drug/variability.py
phaselab/integrations/__init__.py
phaselab/integrations/crispor/__init__.py
phaselab/integrations/crispor/client.py
phaselab/integrations/crispor/offtarget_ir.py
phaselab/integrations/crispor/parsers.py
phaselab/integrations/crispor/pipeline.py
phaselab/io/__init__.py
phaselab/io/export.py
phaselab/io/report.py
phaselab/protein/__init__.py
phaselab/protein/binding.py
phaselab/protein/dynamics.py
phaselab/protein/folding.py
phaselab/quantum/__init__.py
phaselab/quantum/backend.py
phaselab/quantum/coherence.py
phaselab/quantum/gpu.py
phaselab/quantum/grouping.py
phaselab/quantum/vqe.py
phaselab/targets/PTEN.yaml
phaselab/targets/RAI1.yaml
phaselab/targets/SCN2A.yaml
phaselab/targets/__init__.py
phaselab/targets/config.py
phaselab/therapy/__init__.py
phaselab/therapy/dosage.py
phaselab/therapy/efficacy.py
phaselab-0.6.1.dist-info/licenses/LICENSE
phaselab-0.6.1.dist-info/METADATA
phaselab-0.6.1.dist-info/WHEEL
phaselab-0.6.1.dist-info/entry_points.txt
phaselab-0.6.1.dist-info/top_level.txt
phaselab-0.6.1.dist-info/RECORD
