Metadata-Version: 2.4
Name: phaselab
Version: 0.6.1
Summary: Phase-coherence analysis framework for quantum, biological, and dynamical systems
Author-email: Dylan Vaca <dylan@phaselab.dev>
Maintainer-email: Dylan Vaca <dylan@phaselab.dev>
License: MIT
Project-URL: Homepage, https://github.com/followthesapper/phaselab
Project-URL: Documentation, https://phaselab.readthedocs.io
Project-URL: Repository, https://github.com/followthesapper/phaselab
Project-URL: Issues, https://github.com/followthesapper/phaselab/issues
Keywords: quantum computing,coherence,CRISPR,CRISPRa,CRISPRi,gene therapy,prime editing,base editing,knockout,circadian rhythm,Kuramoto,VQE,informational relativity,therapeutic window,ATAC-seq,methylation,nucleosome,enhancer,AAV,immunogenicity,multi-guide
Classifier: Development Status :: 4 - Beta
Classifier: Intended Audience :: Science/Research
Classifier: License :: OSI Approved :: MIT License
Classifier: Programming Language :: Python :: 3
Classifier: Programming Language :: Python :: 3.9
Classifier: Programming Language :: Python :: 3.10
Classifier: Programming Language :: Python :: 3.11
Classifier: Programming Language :: Python :: 3.12
Classifier: Topic :: Scientific/Engineering :: Bio-Informatics
Classifier: Topic :: Scientific/Engineering :: Physics
Classifier: Topic :: Scientific/Engineering :: Medical Science Apps.
Requires-Python: >=3.9
License-File: LICENSE
Requires-Dist: numpy>=1.21
Requires-Dist: scipy>=1.7
Requires-Dist: pandas>=1.3
Requires-Dist: pyyaml>=6.0
Provides-Extra: quantum
Requires-Dist: qiskit>=1.0; extra == "quantum"
Requires-Dist: qiskit-aer>=0.13; extra == "quantum"
Requires-Dist: qiskit-ibm-runtime>=0.20; extra == "quantum"
Requires-Dist: atlas-quantum>=0.6.3; extra == "quantum"
Provides-Extra: plotting
Requires-Dist: matplotlib>=3.5; extra == "plotting"
Requires-Dist: seaborn>=0.12; extra == "plotting"
Provides-Extra: chromatin
Requires-Dist: pyBigWig>=0.3; extra == "chromatin"
Provides-Extra: dev
Requires-Dist: pytest>=7.0; extra == "dev"
Requires-Dist: pytest-cov>=4.0; extra == "dev"
Requires-Dist: black>=23.0; extra == "dev"
Requires-Dist: isort>=5.12; extra == "dev"
Requires-Dist: mypy>=1.0; extra == "dev"
Requires-Dist: ruff>=0.1; extra == "dev"
Provides-Extra: all
Requires-Dist: phaselab[chromatin,dev,plotting,quantum]; extra == "all"
Dynamic: license-file
